make_moments/__init__.py
make_moments/config_defaults.py
make_moments/functions.py
make_moments/main.py
make_moments-1.1.1.dist-info/METADATA
make_moments-1.1.1.dist-info/WHEEL
make_moments-1.1.1.dist-info/entry_points.txt
make_moments-1.1.1.dist-info/licenses/LICENSE
make_moments-1.1.1.dist-info/RECORD
