Metadata-Version: 2.4
Name: make_moments
Version: 1.1.1
Summary: Development Status :: 4 - Beta
Project-URL: Homepage, https://github.com/PeterKamphuis/make_moments
Author-email: "P. Kamphuis" <peterkamphuisastronomy@gmail.com>
License-Expression: GPL-3.0-or-later
License-File: LICENSE
Classifier: Development Status :: 4 - Beta
Classifier: Intended Audience :: Science/Research
Classifier: License :: OSI Approved :: GNU General Public License v3 (GPLv3)
Classifier: Operating System :: POSIX :: Linux
Classifier: Programming Language :: Python :: 3
Classifier: Topic :: Scientific/Engineering :: Astronomy
Requires-Python: >=3.6
Requires-Dist: astropy
Requires-Dist: future-fstrings
Requires-Dist: importlib-metadata
Requires-Dist: importlib-resources>=3.3.0
Requires-Dist: numpy>=1.14
Requires-Dist: omegaconf
Requires-Dist: psutil
Requires-Dist: scipy
